{"index.md":"BpPdkPaT","page.md":"C9ijb-Gm","page_1.md":"DimXINBa","page_index.md":"DK6eI_xo","pages_about.md":"DDnVQFci","pages_archives.md":"swlbxJY3","pages_categories.md":"MbwJ0ZI0","pages_categories_关于本站.md":"BYscdd7o","pages_categories_题解.md":"CBWMFqhT","pages_cc.md":"Bksoq0Lp","pages_index.md":"LDf0XOJJ","pages_link.md":"0naBmr8f","pages_privacy.md":"3A_cMkb5","pages_project.md":"D6bbmp8u","pages_tags.md":"M5i13C4M","pages_tags_hello.md":"B9kRhUNg","pages_tags_无聊至极.md":"COnlD67E","posts_2024_1010.md":"C2oN3O0t","posts_2024_1201.md":"DHymIBOq"}
